{
    "route_id": 240,
    "route_name": "37",
    "bus_data": [
        {
            "id": "863051062952956",
            "lon": 152915995,
            "lat": 82233871.6,
            "dir": 355,
            "speed": 53,
            "lasttime": "12.12.2025 03:15:30",
            "gos_num": "",
            "rid": 240,
            "rnum": "37",
            "rtype": "А",
            "low_floor": "1",
            "wifi": "0",
            "anim_key": 332838,
            "big_jump": "0",
            "anim_points": []
        },
        {
            "id": "863051062856355",
            "lon": 152875733.5,
            "lat": 82250601.2,
            "dir": 317,
            "speed": 25,
            "lasttime": "12.12.2025 03:15:25",
            "gos_num": "",
            "rid": 240,
            "rnum": "37",
            "rtype": "А",
            "low_floor": "1",
            "wifi": "0",
            "anim_key": 332852,
            "big_jump": "0",
            "anim_points": []
        },
        {
            "id": "863051062954325",
            "lon": 152938201,
            "lat": 82189054,
            "dir": 347,
            "speed": 16,
            "lasttime": "12.12.2025 03:15:55",
            "gos_num": "",
            "rid": 240,
            "rnum": "37",
            "rtype": "А",
            "low_floor": "1",
            "wifi": "0",
            "anim_key": 332857,
            "big_jump": "0",
            "anim_points": [
                {
                    "percent": "29",
                    "dir": "246",
                    "lat": 82189095.6,
                    "lon": 152938096
                },
                {
                    "percent": "32",
                    "dir": "255",
                    "lat": 82189940.4,
                    "lon": 152937736
                },
                {
                    "percent": "39",
                    "dir": "257",
                    "lat": 82190970.8,
                    "lon": 152937388
                }
            ]
        },
        {
            "id": "866854056212585",
            "lon": 153004433.5,
            "lat": 82176986.8,
            "dir": 313,
            "speed": 2,
            "lasttime": "12.12.2025 03:16:05",
            "gos_num": "",
            "rid": 240,
            "rnum": "37",
            "rtype": "А",
            "low_floor": "1",
            "wifi": "0",
            "anim_key": 332898,
            "big_jump": "0",
            "anim_points": []
        },
        {
            "id": "866854050989857",
            "lon": 152853455.5,
            "lat": 82267546.8,
            "dir": 318,
            "speed": 26,
            "lasttime": "12.12.2025 03:16:15",
            "gos_num": "",
            "rid": 240,
            "rnum": "37",
            "rtype": "А",
            "low_floor": "0",
            "wifi": "0",
            "anim_key": 332931,
            "big_jump": "0",
            "anim_points": [
                {
                    "percent": "30",
                    "dir": "229",
                    "lat": 82266177.2,
                    "lon": 152855056
                },
                {
                    "percent": "4",
                    "dir": "226",
                    "lat": 82266388.4,
                    "lon": 152854768
                },
                {
                    "percent": "8",
                    "dir": "228",
                    "lat": 82266791.6,
                    "lon": 152854204
                },
                {
                    "percent": "6",
                    "dir": "231",
                    "lat": 82267111.6,
                    "lon": 152853796
                },
                {
                    "percent": "15",
                    "dir": "230",
                    "lat": 82267847.6,
                    "lon": 152852848
                },
                {
                    "percent": "4",
                    "dir": "229",
                    "lat": 82268020.4,
                    "lon": 152852632
                },
                {
                    "percent": "3",
                    "dir": "232",
                    "lat": 82268154.8,
                    "lon": 152852464
                },
                {
                    "percent": "1",
                    "dir": "236",
                    "lat": 82268212.4,
                    "lon": 152852404
                },
                {
                    "percent": "7",
                    "dir": "229",
                    "lat": 82268570.8,
                    "lon": 152851924
                },
                {
                    "percent": "3",
                    "dir": "225",
                    "lat": 82268698.8,
                    "lon": 152851744
                },
                {
                    "percent": "18",
                    "dir": "228",
                    "lat": 82269588.4,
                    "lon": 152850508
                }
            ]
        },
        {
            "id": "866795036131405",
            "lon": 152765569,
            "lat": 82292818.8,
            "dir": 344,
            "speed": 4,
            "lasttime": "12.12.2025 03:15:42",
            "gos_num": "",
            "rid": 240,
            "rnum": "37",
            "rtype": "А",
            "low_floor": "0",
            "wifi": "0",
            "anim_key": 332939,
            "big_jump": "0",
            "anim_points": []
        },
        {
            "id": "866795038357313",
            "lon": 152776745.5,
            "lat": 82297994.8,
            "dir": 205,
            "speed": 26,
            "lasttime": "12.12.2025 03:15:47",
            "gos_num": "",
            "rid": 240,
            "rnum": "37",
            "rtype": "А",
            "low_floor": "0",
            "wifi": "0",
            "anim_key": 332944,
            "big_jump": "0",
            "anim_points": []
        },
        {
            "id": "863051062952956",
            "lon": 152914939,
            "lat": 82241178.8,
            "dir": 352,
            "speed": 61,
            "lasttime": "12.12.2025 03:16:01",
            "gos_num": "",
            "rid": 240,
            "rnum": "37",
            "rtype": "А",
            "low_floor": "1",
            "wifi": "0",
            "anim_key": 332983,
            "big_jump": "0",
            "anim_points": [
                {
                    "percent": "23",
                    "dir": "264",
                    "lat": 82241601.2,
                    "lon": 152914852
                },
                {
                    "percent": "11",
                    "dir": "265",
                    "lat": 82242318,
                    "lon": 152914756
                },
                {
                    "percent": "7",
                    "dir": "265",
                    "lat": 82242778.8,
                    "lon": 152914696
                },
                {
                    "percent": "3",
                    "dir": "264",
                    "lat": 82242996.4,
                    "lon": 152914660
                },
                {
                    "percent": "28",
                    "dir": "264",
                    "lat": 82244897.2,
                    "lon": 152914348
                },
                {
                    "percent": "9",
                    "dir": "264",
                    "lat": 82245492.4,
                    "lon": 152914252
                },
                {
                    "percent": "19",
                    "dir": "262",
                    "lat": 82246798,
                    "lon": 152913976
                }
            ]
        },
        {
            "id": "863051062856355",
            "lon": 152868506.5,
            "lat": 82256130.8,
            "dir": 319,
            "speed": 30,
            "lasttime": "12.12.2025 03:16:20",
            "gos_num": "",
            "rid": 240,
            "rnum": "37",
            "rtype": "А",
            "low_floor": "1",
            "wifi": "0",
            "anim_key": 332997,
            "big_jump": "0",
            "anim_points": [
                {
                    "percent": "38",
                    "dir": "230",
                    "lat": 82254247.6,
                    "lon": 152870884
                },
                {
                    "percent": "8",
                    "dir": "228",
                    "lat": 82254554.8,
                    "lon": 152870464
                },
                {
                    "percent": "3",
                    "dir": "228",
                    "lat": 82254670,
                    "lon": 152870308
                },
                {
                    "percent": "10",
                    "dir": "230",
                    "lat": 82255066.8,
                    "lon": 152869780
                },
                {
                    "percent": "26",
                    "dir": "230",
                    "lat": 82256103.6,
                    "lon": 152868448
                },
                {
                    "percent": "5",
                    "dir": "231",
                    "lat": 82256308.4,
                    "lon": 152868196
                },
                {
                    "percent": "4",
                    "dir": "230",
                    "lat": 82256449.2,
                    "lon": 152868016
                },
                {
                    "percent": "7",
                    "dir": "229",
                    "lat": 82256705.2,
                    "lon": 152867668
                }
            ]
        },
        {
            "id": "863051062954325",
            "lon": 152938201,
            "lat": 82189054,
            "dir": 349,
            "speed": 16,
            "lasttime": "12.12.2025 03:15:55",
            "gos_num": "",
            "rid": 240,
            "rnum": "37",
            "rtype": "А",
            "low_floor": "1",
            "wifi": "0",
            "anim_key": 333002,
            "big_jump": "0",
            "anim_points": []
        },
        {
            "id": "866854056212585",
            "lon": 153004435,
            "lat": 82176986.8,
            "dir": 313,
            "speed": 3,
            "lasttime": "12.12.2025 03:16:05",
            "gos_num": "",
            "rid": 240,
            "rnum": "37",
            "rtype": "А",
            "low_floor": "1",
            "wifi": "0",
            "anim_key": 333044,
            "big_jump": "0",
            "anim_points": []
        },
        {
            "id": "866854050989857",
            "lon": 152853455.5,
            "lat": 82267546.8,
            "dir": 318,
            "speed": 26,
            "lasttime": "12.12.2025 03:16:15",
            "gos_num": "",
            "rid": 240,
            "rnum": "37",
            "rtype": "А",
            "low_floor": "0",
            "wifi": "0",
            "anim_key": 333077,
            "big_jump": "0",
            "anim_points": []
        },
        {
            "id": "866795036131405",
            "lon": 152765573.5,
            "lat": 82292818.8,
            "dir": 344,
            "speed": 4,
            "lasttime": "12.12.2025 03:15:42",
            "gos_num": "",
            "rid": 240,
            "rnum": "37",
            "rtype": "А",
            "low_floor": "0",
            "wifi": "0",
            "anim_key": 333085,
            "big_jump": "0",
            "anim_points": []
        },
        {
            "id": "866795038357313",
            "lon": 152776742.5,
            "lat": 82297994.8,
            "dir": 205,
            "speed": 26,
            "lasttime": "12.12.2025 03:15:47",
            "gos_num": "",
            "rid": 240,
            "rnum": "37",
            "rtype": "А",
            "low_floor": "0",
            "wifi": "0",
            "anim_key": 333090,
            "big_jump": "0",
            "anim_points": []
        },
        {
            "id": "863051062952956",
            "lon": 152914942,
            "lat": 82241177.2,
            "dir": 354,
            "speed": 61,
            "lasttime": "12.12.2025 03:16:01",
            "gos_num": "",
            "rid": 240,
            "rnum": "37",
            "rtype": "А",
            "low_floor": "1",
            "wifi": "0",
            "anim_key": 333275,
            "big_jump": "0",
            "anim_points": []
        },
        {
            "id": "863051062856355",
            "lon": 152868502,
            "lat": 82256130.8,
            "dir": 321,
            "speed": 30,
            "lasttime": "12.12.2025 03:16:20",
            "gos_num": "",
            "rid": 240,
            "rnum": "37",
            "rtype": "А",
            "low_floor": "1",
            "wifi": "0",
            "anim_key": 333289,
            "big_jump": "0",
            "anim_points": []
        },
        {
            "id": "863051062954325",
            "lon": 152937796,
            "lat": 82190834.8,
            "dir": 346,
            "speed": 39,
            "lasttime": "12.12.2025 03:16:10",
            "gos_num": "",
            "rid": 240,
            "rnum": "37",
            "rtype": "А",
            "low_floor": "1",
            "wifi": "0",
            "anim_key": 333294,
            "big_jump": "0",
            "anim_points": [
                {
                    "percent": "100",
                    "dir": "256",
                    "lat": 82192026.8,
                    "lon": 152936980
                }
            ]
        },
        {
            "id": "866854056212585",
            "lon": 153004433.5,
            "lat": 82176986.8,
            "dir": 313,
            "speed": 0,
            "lasttime": "12.12.2025 03:16:41",
            "gos_num": "",
            "rid": 240,
            "rnum": "37",
            "rtype": "А",
            "low_floor": "1",
            "wifi": "0",
            "anim_key": 333337,
            "big_jump": "0",
            "anim_points": []
        },
        {
            "id": "866854050989857",
            "lon": 152853452.5,
            "lat": 82267545.2,
            "dir": 318,
            "speed": 27,
            "lasttime": "12.12.2025 03:16:15",
            "gos_num": "",
            "rid": 240,
            "rnum": "37",
            "rtype": "А",
            "low_floor": "0",
            "wifi": "0",
            "anim_key": 333369,
            "big_jump": "0",
            "anim_points": []
        },
        {
            "id": "866795036131405",
            "lon": 152765513.5,
            "lat": 82292863.6,
            "dir": 312,
            "speed": 0,
            "lasttime": "12.12.2025 03:16:46",
            "gos_num": "",
            "rid": 240,
            "rnum": "37",
            "rtype": "А",
            "low_floor": "0",
            "wifi": "0",
            "anim_key": 333377,
            "big_jump": "0",
            "anim_points": []
        },
        {
            "id": "866795038357313",
            "lon": 152775746.5,
            "lat": 82296658.8,
            "dir": 201,
            "speed": 13,
            "lasttime": "12.12.2025 03:16:11",
            "gos_num": "",
            "rid": 240,
            "rnum": "37",
            "rtype": "А",
            "low_floor": "0",
            "wifi": "0",
            "anim_key": 333382,
            "big_jump": "0",
            "anim_points": []
        },
        {
            "id": "863051062952956",
            "lon": 152914073.5,
            "lat": 82247798,
            "dir": 351,
            "speed": 19,
            "lasttime": "12.12.2025 03:16:51",
            "gos_num": "",
            "rid": 240,
            "rnum": "37",
            "rtype": "А",
            "low_floor": "1",
            "wifi": "0",
            "anim_key": 333422,
            "big_jump": "0",
            "anim_points": [
                {
                    "percent": "27",
                    "dir": "264",
                    "lat": 82247962.8,
                    "lon": 152913784
                },
                {
                    "percent": "4",
                    "dir": "263",
                    "lat": 82248129.2,
                    "lon": 152913748
                },
                {
                    "percent": "17",
                    "dir": "263",
                    "lat": 82248858.8,
                    "lon": 152913628
                },
                {
                    "percent": "3",
                    "dir": "261",
                    "lat": 82248986.8,
                    "lon": 152913592
                },
                {
                    "percent": "5",
                    "dir": "265",
                    "lat": 82249204.4,
                    "lon": 152913556
                },
                {
                    "percent": "2",
                    "dir": "270",
                    "lat": 82249294,
                    "lon": 152913544
                },
                {
                    "percent": "13",
                    "dir": "266",
                    "lat": 82249863.6,
                    "lon": 152913472
                },
                {
                    "percent": "8",
                    "dir": "265",
                    "lat": 82250215.6,
                    "lon": 152913424
                },
                {
                    "percent": "21",
                    "dir": "261",
                    "lat": 82251118,
                    "lon": 152913232
                }
            ]
        },
        {
            "id": "863051062856355",
            "lon": 152867644,
            "lat": 82256814,
            "dir": 319,
            "speed": 20,
            "lasttime": "12.12.2025 03:16:46",
            "gos_num": "",
            "rid": 240,
            "rnum": "37",
            "rtype": "А",
            "low_floor": "1",
            "wifi": "0",
            "anim_key": 333434,
            "big_jump": "0",
            "anim_points": [
                {
                    "percent": "47",
                    "dir": "229",
                    "lat": 82257863.6,
                    "lon": 152866120
                },
                {
                    "percent": "53",
                    "dir": "229",
                    "lat": 82259175.6,
                    "lon": 152864380
                }
            ]
        },
        {
            "id": "863051062954325",
            "lon": 152937796,
            "lat": 82190834.8,
            "dir": 346,
            "speed": 40,
            "lasttime": "12.12.2025 03:16:10",
            "gos_num": "",
            "rid": 240,
            "rnum": "37",
            "rtype": "А",
            "low_floor": "1",
            "wifi": "0",
            "anim_key": 333439,
            "big_jump": "0",
            "anim_points": []
        },
        {
            "id": "866854056212585",
            "lon": 153004435,
            "lat": 82176986.8,
            "dir": 313,
            "speed": 0,
            "lasttime": "12.12.2025 03:16:41",
            "gos_num": "",
            "rid": 240,
            "rnum": "37",
            "rtype": "А",
            "low_floor": "1",
            "wifi": "0",
            "anim_key": 333482,
            "big_jump": "0",
            "anim_points": []
        },
        {
            "id": "866854050989857",
            "lon": 152853452.5,
            "lat": 82267545.2,
            "dir": 318,
            "speed": 27,
            "lasttime": "12.12.2025 03:16:15",
            "gos_num": "",
            "rid": 240,
            "rnum": "37",
            "rtype": "А",
            "low_floor": "0",
            "wifi": "0",
            "anim_key": 333513,
            "big_jump": "0",
            "anim_points": []
        },
        {
            "id": "866795036131405",
            "lon": 152765516.5,
            "lat": 82292862,
            "dir": 312,
            "speed": 0,
            "lasttime": "12.12.2025 03:16:46",
            "gos_num": "",
            "rid": 240,
            "rnum": "37",
            "rtype": "А",
            "low_floor": "0",
            "wifi": "0",
            "anim_key": 333521,
            "big_jump": "0",
            "anim_points": []
        },
        {
            "id": "866795038357313",
            "lon": 152775746.5,
            "lat": 82296658.8,
            "dir": 201,
            "speed": 13,
            "lasttime": "12.12.2025 03:16:11",
            "gos_num": "",
            "rid": 240,
            "rnum": "37",
            "rtype": "А",
            "low_floor": "0",
            "wifi": "0",
            "anim_key": 333526,
            "big_jump": "0",
            "anim_points": []
        },
        {
            "id": "863051062952956",
            "lon": 152914072,
            "lat": 82247799.6,
            "dir": 349,
            "speed": 19,
            "lasttime": "12.12.2025 03:16:51",
            "gos_num": "",
            "rid": 240,
            "rnum": "37",
            "rtype": "А",
            "low_floor": "1",
            "wifi": "0",
            "anim_key": 333711,
            "big_jump": "0",
            "anim_points": []
        },
        {
            "id": "863051062856355",
            "lon": 152867642.5,
            "lat": 82256814,
            "dir": 315,
            "speed": 20,
            "lasttime": "12.12.2025 03:16:46",
            "gos_num": "",
            "rid": 240,
            "rnum": "37",
            "rtype": "А",
            "low_floor": "1",
            "wifi": "0",
            "anim_key": 333722,
            "big_jump": "0",
            "anim_points": []
        },
        {
            "id": "863051062954325",
            "lon": 152936378.5,
            "lat": 82194270,
            "dir": 347,
            "speed": 5,
            "lasttime": "12.12.2025 03:17:10",
            "gos_num": "",
            "rid": 240,
            "rnum": "37",
            "rtype": "А",
            "low_floor": "1",
            "wifi": "0",
            "anim_key": 333727,
            "big_jump": "0",
            "anim_points": [
                {
                    "percent": "34",
                    "dir": "257",
                    "lat": 82193076.4,
                    "lon": 152936608
                },
                {
                    "percent": "26",
                    "dir": "256",
                    "lat": 82193876.4,
                    "lon": 152936296
                },
                {
                    "percent": "41",
                    "dir": "257",
                    "lat": 82195137.2,
                    "lon": 152935864
                }
            ]
        },
        {
            "id": "866854056212585",
            "lon": 153004435,
            "lat": 82176986.8,
            "dir": 313,
            "speed": 0,
            "lasttime": "12.12.2025 03:16:41",
            "gos_num": "",
            "rid": 240,
            "rnum": "37",
            "rtype": "А",
            "low_floor": "1",
            "wifi": "0",
            "anim_key": 333771,
            "big_jump": "0",
            "anim_points": []
        },
        {
            "id": "866854050989857",
            "lon": 152846134,
            "lat": 82272870,
            "dir": 318,
            "speed": 41,
            "lasttime": "12.12.2025 03:17:13",
            "gos_num": "",
            "rid": 240,
            "rnum": "37",
            "rtype": "А",
            "low_floor": "0",
            "wifi": "0",
            "anim_key": 333802,
            "big_jump": "0",
            "anim_points": [
                {
                    "percent": "3",
                    "dir": "227",
                    "lat": 82269722.8,
                    "lon": 152850328
                },
                {
                    "percent": "21",
                    "dir": "226",
                    "lat": 82270759.6,
                    "lon": 152848804
                },
                {
                    "percent": "17",
                    "dir": "227",
                    "lat": 82271630,
                    "lon": 152847544
                },
                {
                    "percent": "21",
                    "dir": "228",
                    "lat": 82272705.2,
                    "lon": 152846080
                },
                {
                    "percent": "17",
                    "dir": "228",
                    "lat": 82273588.4,
                    "lon": 152844856
                },
                {
                    "percent": "21",
                    "dir": "228",
                    "lat": 82274650.8,
                    "lon": 152843392
                }
            ]
        },
        {
            "id": "866795036131405",
            "lon": 152765513.5,
            "lat": 82292863.6,
            "dir": 17,
            "speed": 3,
            "lasttime": "12.12.2025 03:16:53",
            "gos_num": "",
            "rid": 240,
            "rnum": "37",
            "rtype": "А",
            "low_floor": "0",
            "wifi": "0",
            "anim_key": 333810,
            "big_jump": "0",
            "anim_points": []
        },
        {
            "id": "866795038357313",
            "lon": 152772715,
            "lat": 82292617.2,
            "dir": 213,
            "speed": 24,
            "lasttime": "12.12.2025 03:17:04",
            "gos_num": "",
            "rid": 240,
            "rnum": "37",
            "rtype": "А",
            "low_floor": "0",
            "wifi": "0",
            "anim_key": 333815,
            "big_jump": "0",
            "anim_points": []
        },
        {
            "id": "863051062952956",
            "lon": 152913536.5,
            "lat": 82249298.8,
            "dir": 272,
            "speed": 41,
            "lasttime": "12.12.2025 03:17:11",
            "gos_num": "",
            "rid": 240,
            "rnum": "37",
            "rtype": "А",
            "low_floor": "1",
            "wifi": "0",
            "anim_key": 333856,
            "big_jump": "0",
            "anim_points": [
                {
                    "percent": "38",
                    "dir": "182",
                    "lat": 82251150,
                    "lon": 152911804
                },
                {
                    "percent": "22",
                    "dir": "181",
                    "lat": 82251162.8,
                    "lon": 152910964
                },
                {
                    "percent": "40",
                    "dir": "182",
                    "lat": 82251194.8,
                    "lon": 152909452
                }
            ]
        },
        {
            "id": "863051062856355",
            "lon": 152867642.5,
            "lat": 82256814,
            "dir": 315,
            "speed": 20,
            "lasttime": "12.12.2025 03:16:46",
            "gos_num": "",
            "rid": 240,
            "rnum": "37",
            "rtype": "А",
            "low_floor": "1",
            "wifi": "0",
            "anim_key": 333867,
            "big_jump": "0",
            "anim_points": []
        },
        {
            "id": "863051062954325",
            "lon": 152936378.5,
            "lat": 82194270,
            "dir": 353,
            "speed": 5,
            "lasttime": "12.12.2025 03:17:10",
            "gos_num": "",
            "rid": 240,
            "rnum": "37",
            "rtype": "А",
            "low_floor": "1",
            "wifi": "0",
            "anim_key": 333872,
            "big_jump": "0",
            "anim_points": []
        },
        {
            "id": "866854056212585",
            "lon": 153004435,
            "lat": 82176986.8,
            "dir": 313,
            "speed": 0,
            "lasttime": "12.12.2025 03:16:41",
            "gos_num": "",
            "rid": 240,
            "rnum": "37",
            "rtype": "А",
            "low_floor": "1",
            "wifi": "0",
            "anim_key": 333917,
            "big_jump": "0",
            "anim_points": []
        },
        {
            "id": "866854050989857",
            "lon": 152846128,
            "lat": 82272866.8,
            "dir": 318,
            "speed": 41,
            "lasttime": "12.12.2025 03:17:13",
            "gos_num": "",
            "rid": 240,
            "rnum": "37",
            "rtype": "А",
            "low_floor": "0",
            "wifi": "0",
            "anim_key": 333948,
            "big_jump": "0",
            "anim_points": []
        },
        {
            "id": "866795036131405",
            "lon": 152765516.5,
            "lat": 82292862,
            "dir": 17,
            "speed": 3,
            "lasttime": "12.12.2025 03:16:53",
            "gos_num": "",
            "rid": 240,
            "rnum": "37",
            "rtype": "А",
            "low_floor": "0",
            "wifi": "0",
            "anim_key": 333956,
            "big_jump": "0",
            "anim_points": []
        },
        {
            "id": "866795038357313",
            "lon": 152772715,
            "lat": 82292617.2,
            "dir": 213,
            "speed": 24,
            "lasttime": "12.12.2025 03:17:04",
            "gos_num": "",
            "rid": 240,
            "rnum": "37",
            "rtype": "А",
            "low_floor": "0",
            "wifi": "0",
            "anim_key": 333961,
            "big_jump": "0",
            "anim_points": []
        },
        {
            "id": "863051062952956",
            "lon": 152913533.5,
            "lat": 82249300.4,
            "dir": 356,
            "speed": 41,
            "lasttime": "12.12.2025 03:17:11",
            "gos_num": "",
            "rid": 240,
            "rnum": "37",
            "rtype": "А",
            "low_floor": "1",
            "wifi": "0",
            "anim_key": 334002,
            "big_jump": "0",
            "anim_points": []
        },
        {
            "id": "863051062856355",
            "lon": 152867642.5,
            "lat": 82256814,
            "dir": 315,
            "speed": 20,
            "lasttime": "12.12.2025 03:16:46",
            "gos_num": "",
            "rid": 240,
            "rnum": "37",
            "rtype": "А",
            "low_floor": "1",
            "wifi": "0",
            "anim_key": 334013,
            "big_jump": "0",
            "anim_points": []
        },
        {
            "id": "863051062954325",
            "lon": 152936377,
            "lat": 82194271.6,
            "dir": 353,
            "speed": 5,
            "lasttime": "12.12.2025 03:17:10",
            "gos_num": "",
            "rid": 240,
            "rnum": "37",
            "rtype": "А",
            "low_floor": "1",
            "wifi": "0",
            "anim_key": 334018,
            "big_jump": "0",
            "anim_points": []
        },
        {
            "id": "866854056212585",
            "lon": 153004435,
            "lat": 82176986.8,
            "dir": 313,
            "speed": 0,
            "lasttime": "12.12.2025 03:16:41",
            "gos_num": "",
            "rid": 240,
            "rnum": "37",
            "rtype": "А",
            "low_floor": "1",
            "wifi": "0",
            "anim_key": 334063,
            "big_jump": "0",
            "anim_points": []
        },
        {
            "id": "866854050989857",
            "lon": 152846128,
            "lat": 82272866.8,
            "dir": 318,
            "speed": 41,
            "lasttime": "12.12.2025 03:17:13",
            "gos_num": "",
            "rid": 240,
            "rnum": "37",
            "rtype": "А",
            "low_floor": "0",
            "wifi": "0",
            "anim_key": 334094,
            "big_jump": "0",
            "anim_points": []
        },
        {
            "id": "866795036131405",
            "lon": 152765516.5,
            "lat": 82292862,
            "dir": 17,
            "speed": 3,
            "lasttime": "12.12.2025 03:16:53",
            "gos_num": "",
            "rid": 240,
            "rnum": "37",
            "rtype": "А",
            "low_floor": "0",
            "wifi": "0",
            "anim_key": 334102,
            "big_jump": "0",
            "anim_points": []
        },
        {
            "id": "866795038357313",
            "lon": 152772493,
            "lat": 82292394.8,
            "dir": 295,
            "speed": 8,
            "lasttime": "12.12.2025 03:17:20",
            "gos_num": "",
            "rid": 240,
            "rnum": "37",
            "rtype": "А",
            "low_floor": "0",
            "wifi": "0",
            "anim_key": 334107,
            "big_jump": "0",
            "anim_points": [
                {
                    "percent": "20",
                    "dir": "121",
                    "lat": 82291841.2,
                    "lon": 152772112
                },
                {
                    "percent": "5",
                    "dir": "107",
                    "lat": 82291674.8,
                    "lon": 152772016
                },
                {
                    "percent": "4",
                    "dir": "94",
                    "lat": 82291540.4,
                    "lon": 152772004
                },
                {
                    "percent": "27",
                    "dir": "114",
                    "lat": 82290676.4,
                    "lon": 152771416
                },
                {
                    "percent": "2",
                    "dir": "124",
                    "lat": 82290612.4,
                    "lon": 152771356
                },
                {
                    "percent": "5",
                    "dir": "235",
                    "lat": 82290753.2,
                    "lon": 152771200
                },
                {
                    "percent": "5",
                    "dir": "209",
                    "lat": 82290842.8,
                    "lon": 152770948
                },
                {
                    "percent": "33",
                    "dir": "205",
                    "lat": 82291342,
                    "lon": 152769316
                }
            ]
        },
        {
            "id": "863051062952956",
            "lon": 152907800.5,
            "lat": 82251750,
            "dir": 267,
            "speed": 45,
            "lasttime": "12.12.2025 03:17:44",
            "gos_num": "",
            "rid": 240,
            "rnum": "37",
            "rtype": "А",
            "low_floor": "1",
            "wifi": "0",
            "anim_key": 334147,
            "big_jump": "0",
            "anim_points": [
                {
                    "percent": "2",
                    "dir": "184",
                    "lat": 82251201.2,
                    "lon": 152909236
                },
                {
                    "percent": "1",
                    "dir": "188",
                    "lat": 82251207.6,
                    "lon": 152909116
                },
                {
                    "percent": "1",
                    "dir": "188",
                    "lat": 82251220.4,
                    "lon": 152909008
                },
                {
                    "percent": "1",
                    "dir": "189",
                    "lat": 82251239.6,
                    "lon": 152908912
                },
                {
                    "percent": "1",
                    "dir": "203",
                    "lat": 82251258.8,
                    "lon": 152908792
                },
                {
                    "percent": "2",
                    "dir": "203",
                    "lat": 82251316.4,
                    "lon": 152908600
                },
                {
                    "percent": "5",
                    "dir": "221",
                    "lat": 82251521.2,
                    "lon": 152908240
                },
                {
                    "percent": "8",
                    "dir": "217",
                    "lat": 82251815.6,
                    "lon": 152907640
                },
                {
                    "percent": "8",
                    "dir": "219",
                    "lat": 82252116.4,
                    "lon": 152907088
                },
                {
                    "percent": "7",
                    "dir": "214",
                    "lat": 82252340.4,
                    "lon": 152906560
                },
                {
                    "percent": "6",
                    "dir": "210",
                    "lat": 82252519.6,
                    "lon": 152906068
                },
                {
                    "percent": "6",
                    "dir": "206",
                    "lat": 82252673.2,
                    "lon": 152905612
                },
                {
                    "percent": "7",
                    "dir": "202",
                    "lat": 82252814,
                    "lon": 152905048
                },
                {
                    "percent": "7",
                    "dir": "198",
                    "lat": 82252942,
                    "lon": 152904460
                },
                {
                    "percent": "7",
                    "dir": "193",
                    "lat": 82253044.4,
                    "lon": 152903836
                },
                {
                    "percent": "7",
                    "dir": "190",
                    "lat": 82253108.4,
                    "lon": 152903236
                },
                {
                    "percent": "7",
                    "dir": "186",
                    "lat": 82253153.2,
                    "lon": 152902636
                },
                {
                    "percent": "7",
                    "dir": "183",
                    "lat": 82253172.4,
                    "lon": 152901988
                },
                {
                    "percent": "7",
                    "dir": "177",
                    "lat": 82253153.2,
                    "lon": 152901352
                }
            ]
        },
        {
            "id": "863051062856355",
            "lon": 152861900.5,
            "lat": 82261119.6,
            "dir": 318,
            "speed": 10,
            "lasttime": "12.12.2025 03:17:47",
            "gos_num": "",
            "rid": 240,
            "rnum": "37",
            "rtype": "А",
            "low_floor": "1",
            "wifi": "0",
            "anim_key": 334157,
            "big_jump": "0",
            "anim_points": [
                {
                    "percent": "21",
                    "dir": "229",
                    "lat": 82259873.2,
                    "lon": 152863432
                },
                {
                    "percent": "36",
                    "dir": "230",
                    "lat": 82261095.6,
                    "lon": 152861836
                },
                {
                    "percent": "2",
                    "dir": "233",
                    "lat": 82261178.8,
                    "lon": 152861740
                },
                {
                    "percent": "1",
                    "dir": "233",
                    "lat": 82261223.6,
                    "lon": 152861680
                },
                {
                    "percent": "3",
                    "dir": "228",
                    "lat": 82261313.2,
                    "lon": 152861560
                },
                {
                    "percent": "38",
                    "dir": "228",
                    "lat": 82262593.2,
                    "lon": 152859808
                }
            ]
        },
        {
            "id": "863051062954325",
            "lon": 152935918,
            "lat": 82195462,
            "dir": 347,
            "speed": 24,
            "lasttime": "12.12.2025 03:17:37",
            "gos_num": "",
            "rid": 240,
            "rnum": "37",
            "rtype": "А",
            "low_floor": "1",
            "wifi": "0",
            "anim_key": 334162,
            "big_jump": "0",
            "anim_points": [
                {
                    "percent": "100",
                    "dir": "257",
                    "lat": 82196532.4,
                    "lon": 152935372
                }
            ]
        },
        {
            "id": "866854056212585",
            "lon": 153004445.5,
            "lat": 82176974,
            "dir": 304,
            "speed": 3,
            "lasttime": "12.12.2025 03:17:46",
            "gos_num": "",
            "rid": 240,
            "rnum": "37",
            "rtype": "А",
            "low_floor": "1",
            "wifi": "0",
            "anim_key": 334208,
            "big_jump": "0",
            "anim_points": []
        },
        {
            "id": "866854050989857",
            "lon": 152846128,
            "lat": 82272866.8,
            "dir": 318,
            "speed": 41,
            "lasttime": "12.12.2025 03:17:13",
            "gos_num": "",
            "rid": 240,
            "rnum": "37",
            "rtype": "А",
            "low_floor": "0",
            "wifi": "0",
            "anim_key": 334240,
            "big_jump": "0",
            "anim_points": []
        },
        {
            "id": "866795036131405",
            "lon": 152765513.5,
            "lat": 82292863.6,
            "dir": 312,
            "speed": 0,
            "lasttime": "12.12.2025 03:17:25",
            "gos_num": "",
            "rid": 240,
            "rnum": "37",
            "rtype": "А",
            "low_floor": "0",
            "wifi": "0",
            "anim_key": 334248,
            "big_jump": "0",
            "anim_points": []
        },
        {
            "id": "866795038357313",
            "lon": 152772497.5,
            "lat": 82292391.6,
            "dir": 177,
            "speed": 8,
            "lasttime": "12.12.2025 03:17:20",
            "gos_num": "",
            "rid": 240,
            "rnum": "37",
            "rtype": "А",
            "low_floor": "0",
            "wifi": "0",
            "anim_key": 334253,
            "big_jump": "0",
            "anim_points": []
        },
        {
            "id": "863051062952956",
            "lon": 152899895.5,
            "lat": 82253026.8,
            "dir": 256,
            "speed": 63,
            "lasttime": "12.12.2025 03:18:06",
            "gos_num": "",
            "rid": 240,
            "rnum": "37",
            "rtype": "А",
            "low_floor": "1",
            "wifi": "0",
            "anim_key": 334439,
            "big_jump": "0",
            "anim_points": [
                {
                    "percent": "7",
                    "dir": "173",
                    "lat": 82253102,
                    "lon": 152900704
                },
                {
                    "percent": "7",
                    "dir": "172",
                    "lat": 82253031.6,
                    "lon": 152900032
                },
                {
                    "percent": "6",
                    "dir": "168",
                    "lat": 82252948.4,
                    "lon": 152899432
                },
                {
                    "percent": "22",
                    "dir": "166",
                    "lat": 82252615.6,
                    "lon": 152897296
                },
                {
                    "percent": "15",
                    "dir": "166",
                    "lat": 82252378.8,
                    "lon": 152895820
                },
                {
                    "percent": "20",
                    "dir": "166",
                    "lat": 82252071.6,
                    "lon": 152893900
                },
                {
                    "percent": "22",
                    "dir": "166",
                    "lat": 82251713.2,
                    "lon": 152891776
                }
            ]
        },
        {
            "id": "863051062856355",
            "lon": 152861897.5,
            "lat": 82261118,
            "dir": 312,
            "speed": 11,
            "lasttime": "12.12.2025 03:17:47",
            "gos_num": "",
            "rid": 240,
            "rnum": "37",
            "rtype": "А",
            "low_floor": "1",
            "wifi": "0",
            "anim_key": 334450,
            "big_jump": "0",
            "anim_points": []
        },
        {
            "id": "863051062954325",
            "lon": 152935918,
            "lat": 82195462,
            "dir": 347,
            "speed": 25,
            "lasttime": "12.12.2025 03:17:37",
            "gos_num": "",
            "rid": 240,
            "rnum": "37",
            "rtype": "А",
            "low_floor": "1",
            "wifi": "0",
            "anim_key": 334455,
            "big_jump": "0",
            "anim_points": []
        },
        {
            "id": "866854056212585",
            "lon": 153004445.5,
            "lat": 82176974,
            "dir": 304,
            "speed": 3,
            "lasttime": "12.12.2025 03:17:46",
            "gos_num": "",
            "rid": 240,
            "rnum": "37",
            "rtype": "А",
            "low_floor": "1",
            "wifi": "0",
            "anim_key": 334501,
            "big_jump": "0",
            "anim_points": []
        },
        {
            "id": "866854050989857",
            "lon": 152842475.5,
            "lat": 82275630,
            "dir": 317,
            "speed": 10,
            "lasttime": "12.12.2025 03:17:51",
            "gos_num": "",
            "rid": 240,
            "rnum": "37",
            "rtype": "А",
            "low_floor": "0",
            "wifi": "0",
            "anim_key": 334533,
            "big_jump": "0",
            "anim_points": [
                {
                    "percent": "23",
                    "dir": "228",
                    "lat": 82275450.8,
                    "lon": 152842300
                },
                {
                    "percent": "4",
                    "dir": "229",
                    "lat": 82275598,
                    "lon": 152842096
                },
                {
                    "percent": "4",
                    "dir": "227",
                    "lat": 82275745.2,
                    "lon": 152841904
                },
                {
                    "percent": "31",
                    "dir": "229",
                    "lat": 82276846,
                    "lon": 152840440
                },
                {
                    "percent": "21",
                    "dir": "229",
                    "lat": 82277588.4,
                    "lon": 152839456
                },
                {
                    "percent": "17",
                    "dir": "227",
                    "lat": 82278170.8,
                    "lon": 152838628
                }
            ]
        },
        {
            "id": "866795036131405",
            "lon": 152765516.5,
            "lat": 82292862,
            "dir": 312,
            "speed": 0,
            "lasttime": "12.12.2025 03:17:25",
            "gos_num": "",
            "rid": 240,
            "rnum": "37",
            "rtype": "А",
            "low_floor": "0",
            "wifi": "0",
            "anim_key": 334541,
            "big_jump": "0",
            "anim_points": []
        },
        {
            "id": "866795038357313",
            "lon": 152770640.5,
            "lat": 82290914.8,
            "dir": 297,
            "speed": 13,
            "lasttime": "12.12.2025 03:17:45",
            "gos_num": "",
            "rid": 240,
            "rnum": "37",
            "rtype": "А",
            "low_floor": "0",
            "wifi": "0",
            "anim_key": 334546,
            "big_jump": "0",
            "anim_points": [
                {
                    "percent": "13",
                    "dir": "207",
                    "lat": 82291489.2,
                    "lon": 152768872
                },
                {
                    "percent": "19",
                    "dir": "207",
                    "lat": 82291706.8,
                    "lon": 152768212
                },
                {
                    "percent": "68",
                    "dir": "207",
                    "lat": 82292481.2,
                    "lon": 152765884
                }
            ]
        },
        {
            "id": "863051062952956",
            "lon": 152899895.5,
            "lat": 82253026.8,
            "dir": 258,
            "speed": 63,
            "lasttime": "12.12.2025 03:18:06",
            "gos_num": "",
            "rid": 240,
            "rnum": "37",
            "rtype": "А",
            "low_floor": "1",
            "wifi": "0",
            "anim_key": 334586,
            "big_jump": "0",
            "anim_points": []
        },
        {
            "id": "863051062856355",
            "lon": 152861675.5,
            "lat": 82261314.8,
            "dir": 319,
            "speed": 22,
            "lasttime": "12.12.2025 03:17:50",
            "gos_num": "",
            "rid": 240,
            "rnum": "37",
            "rtype": "А",
            "low_floor": "1",
            "wifi": "0",
            "anim_key": 334597,
            "big_jump": "0",
            "anim_points": [
                {
                    "percent": "12",
                    "dir": "228",
                    "lat": 82262817.2,
                    "lon": 152859496
                },
                {
                    "percent": "7",
                    "dir": "227",
                    "lat": 82262938.8,
                    "lon": 152859340
                },
                {
                    "percent": "7",
                    "dir": "230",
                    "lat": 82263066.8,
                    "lon": 152859160
                },
                {
                    "percent": "74",
                    "dir": "229",
                    "lat": 82264423.6,
                    "lon": 152857384
                }
            ]
        },
        {
            "id": "863051062954325",
            "lon": 152934754,
            "lat": 82198486,
            "dir": 318,
            "speed": 32,
            "lasttime": "12.12.2025 03:18:02",
            "gos_num": "",
            "rid": 240,
            "rnum": "37",
            "rtype": "А",
            "low_floor": "1",
            "wifi": "0",
            "anim_key": 334602,
            "big_jump": "0",
            "anim_points": [
                {
                    "percent": "10",
                    "dir": "256",
                    "lat": 82197300.4,
                    "lon": 152935072
                },
                {
                    "percent": "18",
                    "dir": "256",
                    "lat": 82198695.6,
                    "lon": 152934568
                },
                {
                    "percent": "10",
                    "dir": "256",
                    "lat": 82199431.6,
                    "lon": 152934280
                },
                {
                    "percent": "24",
                    "dir": "257",
                    "lat": 82201242.8,
                    "lon": 152933656
                },
                {
                    "percent": "5",
                    "dir": "254",
                    "lat": 82201652.4,
                    "lon": 152933464
                },
                {
                    "percent": "5",
                    "dir": "248",
                    "lat": 82202023.6,
                    "lon": 152933248
                },
                {
                    "percent": "5",
                    "dir": "241",
                    "lat": 82202369.2,
                    "lon": 152932960
                },
                {
                    "percent": "5",
                    "dir": "232",
                    "lat": 82202689.2,
                    "lon": 152932576
                },
                {
                    "percent": "10",
                    "dir": "227",
                    "lat": 82203246,
                    "lon": 152931772
                },
                {
                    "percent": "8",
                    "dir": "228",
                    "lat": 82203719.6,
                    "lon": 152931136
                }
            ]
        },
        {
            "id": "866854056212585",
            "lon": 153004445.5,
            "lat": 82176974,
            "dir": 304,
            "speed": 3,
            "lasttime": "12.12.2025 03:17:46",
            "gos_num": "",
            "rid": 240,
            "rnum": "37",
            "rtype": "А",
            "low_floor": "1",
            "wifi": "0",
            "anim_key": 334648,
            "big_jump": "0",
            "anim_points": []
        },
        {
            "id": "866854050989857",
            "lon": 152842475.5,
            "lat": 82275630,
            "dir": 295,
            "speed": 10,
            "lasttime": "12.12.2025 03:17:51",
            "gos_num": "",
            "rid": 240,
            "rnum": "37",
            "rtype": "А",
            "low_floor": "0",
            "wifi": "0",
            "anim_key": 334680,
            "big_jump": "0",
            "anim_points": []
        },
        {
            "id": "866795036131405",
            "lon": 152765513.5,
            "lat": 82292863.6,
            "dir": 60,
            "speed": 4,
            "lasttime": "12.12.2025 03:17:52",
            "gos_num": "",
            "rid": 240,
            "rnum": "37",
            "rtype": "А",
            "low_floor": "0",
            "wifi": "0",
            "anim_key": 334688,
            "big_jump": "0",
            "anim_points": []
        },
        {
            "id": "866795038357313",
            "lon": 152770643.5,
            "lat": 82290914.8,
            "dir": 298,
            "speed": 13,
            "lasttime": "12.12.2025 03:17:45",
            "gos_num": "",
            "rid": 240,
            "rnum": "37",
            "rtype": "А",
            "low_floor": "0",
            "wifi": "0",
            "anim_key": 334693,
            "big_jump": "0",
            "anim_points": []
        },
        {
            "id": "863051062952956",
            "lon": 152899892.5,
            "lat": 82253023.6,
            "dir": 258,
            "speed": 63,
            "lasttime": "12.12.2025 03:18:06",
            "gos_num": "",
            "rid": 240,
            "rnum": "37",
            "rtype": "А",
            "low_floor": "1",
            "wifi": "0",
            "anim_key": 334733,
            "big_jump": "0",
            "anim_points": []
        },
        {
            "id": "863051062856355",
            "lon": 152861675.5,
            "lat": 82261314.8,
            "dir": 323,
            "speed": 23,
            "lasttime": "12.12.2025 03:17:50",
            "gos_num": "",
            "rid": 240,
            "rnum": "37",
            "rtype": "А",
            "low_floor": "1",
            "wifi": "0",
            "anim_key": 334744,
            "big_jump": "0",
            "anim_points": []
        },
        {
            "id": "863051062954325",
            "lon": 152934754,
            "lat": 82198486,
            "dir": 348,
            "speed": 33,
            "lasttime": "12.12.2025 03:18:02",
            "gos_num": "",
            "rid": 240,
            "rnum": "37",
            "rtype": "А",
            "low_floor": "1",
            "wifi": "0",
            "anim_key": 334749,
            "big_jump": "0",
            "anim_points": []
        },
        {
            "id": "866854056212585",
            "lon": 153003563.5,
            "lat": 82177431.6,
            "dir": 313,
            "speed": 32,
            "lasttime": "12.12.2025 03:17:55",
            "gos_num": "",
            "rid": 240,
            "rnum": "37",
            "rtype": "А",
            "low_floor": "1",
            "wifi": "0",
            "anim_key": 334795,
            "big_jump": "0",
            "anim_points": [
                {
                    "percent": "100",
                    "dir": "223",
                    "lat": 82177434.8,
                    "lon": 153003568
                }
            ]
        },
        {
            "id": "866854050989857",
            "lon": 152842475.5,
            "lat": 82275630,
            "dir": 295,
            "speed": 10,
            "lasttime": "12.12.2025 03:17:51",
            "gos_num": "",
            "rid": 240,
            "rnum": "37",
            "rtype": "А",
            "low_floor": "0",
            "wifi": "0",
            "anim_key": 334827,
            "big_jump": "0",
            "anim_points": []
        },
        {
            "id": "866795036131405",
            "lon": 152765513.5,
            "lat": 82292863.6,
            "dir": 60,
            "speed": 3,
            "lasttime": "12.12.2025 03:17:52",
            "gos_num": "",
            "rid": 240,
            "rnum": "37",
            "rtype": "А",
            "low_floor": "0",
            "wifi": "0",
            "anim_key": 334835,
            "big_jump": "0",
            "anim_points": []
        },
        {
            "id": "866795038357313",
            "lon": 152770643.5,
            "lat": 82290914.8,
            "dir": 298,
            "speed": 13,
            "lasttime": "12.12.2025 03:17:45",
            "gos_num": "",
            "rid": 240,
            "rnum": "37",
            "rtype": "А",
            "low_floor": "0",
            "wifi": "0",
            "anim_key": 334840,
            "big_jump": "0",
            "anim_points": []
        },
        {
            "id": "863051062952956",
            "lon": 152893793.5,
            "lat": 82252084.4,
            "dir": 252,
            "speed": 55,
            "lasttime": "12.12.2025 03:18:24",
            "gos_num": "",
            "rid": 240,
            "rnum": "37",
            "rtype": "А",
            "low_floor": "1",
            "wifi": "0",
            "anim_key": 335173,
            "big_jump": "0",
            "anim_points": []
        },
        {
            "id": "863051062856355",
            "lon": 152860826.5,
            "lat": 82261974,
            "dir": 318,
            "speed": 23,
            "lasttime": "12.12.2025 03:18:25",
            "gos_num": "",
            "rid": 240,
            "rnum": "37",
            "rtype": "А",
            "low_floor": "1",
            "wifi": "0",
            "anim_key": 335184,
            "big_jump": "0",
            "anim_points": []
        },
        {
            "id": "863051062954325",
            "lon": 152933255.5,
            "lat": 82202183.6,
            "dir": 330,
            "speed": 38,
            "lasttime": "12.12.2025 03:18:27",
            "gos_num": "",
            "rid": 240,
            "rnum": "37",
            "rtype": "А",
            "low_floor": "1",
            "wifi": "0",
            "anim_key": 335189,
            "big_jump": "0",
            "anim_points": []
        },
        {
            "id": "866854056212585",
            "lon": 153003565,
            "lat": 82177431.6,
            "dir": 313,
            "speed": 32,
            "lasttime": "12.12.2025 03:17:55",
            "gos_num": "",
            "rid": 240,
            "rnum": "37",
            "rtype": "А",
            "low_floor": "1",
            "wifi": "0",
            "anim_key": 335235,
            "big_jump": "0",
            "anim_points": []
        },
        {
            "id": "866854050989857",
            "lon": 152838361,
            "lat": 82278455.6,
            "dir": 312,
            "speed": 46,
            "lasttime": "12.12.2025 03:18:17",
            "gos_num": "",
            "rid": 240,
            "rnum": "37",
            "rtype": "А",
            "low_floor": "0",
            "wifi": "0",
            "anim_key": 335268,
            "big_jump": "0",
            "anim_points": []
        },
        {
            "id": "863051062952956",
            "lon": 152887208.5,
            "lat": 82251018.8,
            "dir": 255,
            "speed": 56,
            "lasttime": "12.12.2025 03:18:43",
            "gos_num": "",
            "rid": 240,
            "rnum": "37",
            "rtype": "А",
            "low_floor": "1",
            "wifi": "0",
            "anim_key": 335472,
            "big_jump": "0",
            "anim_points": [
                {
                    "percent": "59",
                    "dir": "166",
                    "lat": 82249870,
                    "lon": 152880316
                },
                {
                    "percent": "41",
                    "dir": "165",
                    "lat": 82249614,
                    "lon": 152878864
                }
            ]
        },
        {
            "id": "863051062856355",
            "lon": 152860822,
            "lat": 82261972.4,
            "dir": 318,
            "speed": 23,
            "lasttime": "12.12.2025 03:18:25",
            "gos_num": "",
            "rid": 240,
            "rnum": "37",
            "rtype": "А",
            "low_floor": "1",
            "wifi": "0",
            "anim_key": 335483,
            "big_jump": "0",
            "anim_points": []
        },
        {
            "id": "863051062954325",
            "lon": 152932783,
            "lat": 82202575.6,
            "dir": 318,
            "speed": 40,
            "lasttime": "12.12.2025 03:18:30",
            "gos_num": "",
            "rid": 240,
            "rnum": "37",
            "rtype": "А",
            "low_floor": "1",
            "wifi": "0",
            "anim_key": 335488,
            "big_jump": "0",
            "anim_points": [
                {
                    "percent": "100",
                    "dir": "228",
                    "lat": 82206990,
                    "lon": 152926600
                }
            ]
        },
        {
            "id": "866854056212585",
            "lon": 152997530.5,
            "lat": 82180418.8,
            "dir": 217,
            "speed": 18,
            "lasttime": "12.12.2025 03:18:55",
            "gos_num": "",
            "rid": 240,
            "rnum": "37",
            "rtype": "А",
            "low_floor": "1",
            "wifi": "0",
            "anim_key": 335534,
            "big_jump": "0",
            "anim_points": []
        },
        {
            "id": "866854050989857",
            "lon": 152832800.5,
            "lat": 82280906.8,
            "dir": 296,
            "speed": 12,
            "lasttime": "12.12.2025 03:18:55",
            "gos_num": "",
            "rid": 240,
            "rnum": "37",
            "rtype": "А",
            "low_floor": "0",
            "wifi": "0",
            "anim_key": 335568,
            "big_jump": "0",
            "anim_points": [
                {
                    "percent": "55",
                    "dir": "207",
                    "lat": 82280897.2,
                    "lon": 152832760
                },
                {
                    "percent": "45",
                    "dir": "206",
                    "lat": 82281172.4,
                    "lon": 152831896
                }
            ]
        },
        {
            "id": "863051062952956",
            "lon": 152887213,
            "lat": 82251015.6,
            "dir": 257,
            "speed": 56,
            "lasttime": "12.12.2025 03:18:43",
            "gos_num": "",
            "rid": 240,
            "rnum": "37",
            "rtype": "А",
            "low_floor": "1",
            "wifi": "0",
            "anim_key": 335621,
            "big_jump": "0",
            "anim_points": []
        },
        {
            "id": "863051062856355",
            "lon": 152854628.5,
            "lat": 82266698.8,
            "dir": 319,
            "speed": 25,
            "lasttime": "12.12.2025 03:19:26",
            "gos_num": "",
            "rid": 240,
            "rnum": "37",
            "rtype": "А",
            "low_floor": "1",
            "wifi": "0",
            "anim_key": 335632,
            "big_jump": "0",
            "anim_points": [
                {
                    "percent": "12",
                    "dir": "226",
                    "lat": 82266388.4,
                    "lon": 152854768
                },
                {
                    "percent": "22",
                    "dir": "228",
                    "lat": 82266791.6,
                    "lon": 152854204
                },
                {
                    "percent": "17",
                    "dir": "231",
                    "lat": 82267111.6,
                    "lon": 152853796
                },
                {
                    "percent": "39",
                    "dir": "230",
                    "lat": 82267847.6,
                    "lon": 152852848
                },
                {
                    "percent": "9",
                    "dir": "229",
                    "lat": 82268020.4,
                    "lon": 152852632
                }
            ]
        },
        {
            "id": "863051062954325",
            "lon": 152932783,
            "lat": 82202575.6,
            "dir": 321,
            "speed": 40,
            "lasttime": "12.12.2025 03:18:30",
            "gos_num": "",
            "rid": 240,
            "rnum": "37",
            "rtype": "А",
            "low_floor": "1",
            "wifi": "0",
            "anim_key": 335637,
            "big_jump": "0",
            "anim_points": []
        },
        {
            "id": "866854056212585",
            "lon": 152997530.5,
            "lat": 82180418.8,
            "dir": 217,
            "speed": 18,
            "lasttime": "12.12.2025 03:18:55",
            "gos_num": "",
            "rid": 240,
            "rnum": "37",
            "rtype": "А",
            "low_floor": "1",
            "wifi": "0",
            "anim_key": 335683,
            "big_jump": "0",
            "anim_points": []
        },
        {
            "id": "866854050989857",
            "lon": 152832800.5,
            "lat": 82280906.8,
            "dir": 284,
            "speed": 13,
            "lasttime": "12.12.2025 03:18:55",
            "gos_num": "",
            "rid": 240,
            "rnum": "37",
            "rtype": "А",
            "low_floor": "0",
            "wifi": "0",
            "anim_key": 335717,
            "big_jump": "0",
            "anim_points": []
        },
        {
            "id": "863051062952956",
            "lon": 152887213,
            "lat": 82251015.6,
            "dir": 257,
            "speed": 56,
            "lasttime": "12.12.2025 03:18:43",
            "gos_num": "",
            "rid": 240,
            "rnum": "37",
            "rtype": "А",
            "low_floor": "1",
            "wifi": "0",
            "anim_key": 335770,
            "big_jump": "0",
            "anim_points": []
        },
        {
            "id": "863051062856355",
            "lon": 152854628.5,
            "lat": 82266698.8,
            "dir": 324,
            "speed": 26,
            "lasttime": "12.12.2025 03:19:26",
            "gos_num": "",
            "rid": 240,
            "rnum": "37",
            "rtype": "А",
            "low_floor": "1",
            "wifi": "0",
            "anim_key": 335781,
            "big_jump": "0",
            "anim_points": []
        },
        {
            "id": "863051062954325",
            "lon": 152932783,
            "lat": 82202578.8,
            "dir": 321,
            "speed": 40,
            "lasttime": "12.12.2025 03:18:30",
            "gos_num": "",
            "rid": 240,
            "rnum": "37",
            "rtype": "А",
            "low_floor": "1",
            "wifi": "0",
            "anim_key": 335786,
            "big_jump": "0",
            "anim_points": []
        },
        {
            "id": "866854056212585",
            "lon": 152997530.5,
            "lat": 82180418.8,
            "dir": 217,
            "speed": 19,
            "lasttime": "12.12.2025 03:18:55",
            "gos_num": "",
            "rid": 240,
            "rnum": "37",
            "rtype": "А",
            "low_floor": "1",
            "wifi": "0",
            "anim_key": 335832,
            "big_jump": "0",
            "anim_points": []
        },
        {
            "id": "866854050989857",
            "lon": 152832796,
            "lat": 82280905.2,
            "dir": 284,
            "speed": 13,
            "lasttime": "12.12.2025 03:18:55",
            "gos_num": "",
            "rid": 240,
            "rnum": "37",
            "rtype": "А",
            "low_floor": "0",
            "wifi": "0",
            "anim_key": 335866,
            "big_jump": "0",
            "anim_points": []
        },
        {
            "id": "863051062952956",
            "lon": 152877187,
            "lat": 82249490.8,
            "dir": 291,
            "speed": 26,
            "lasttime": "12.12.2025 03:19:29",
            "gos_num": "",
            "rid": 240,
            "rnum": "37",
            "rtype": "А",
            "low_floor": "1",
            "wifi": "0",
            "anim_key": 336068,
            "big_jump": "0",
            "anim_points": []
        },
        {
            "id": "863051062856355",
            "lon": 152854073.5,
            "lat": 82267066.8,
            "dir": 318,
            "speed": 14,
            "lasttime": "12.12.2025 03:19:50",
            "gos_num": "",
            "rid": 240,
            "rnum": "37",
            "rtype": "А",
            "low_floor": "1",
            "wifi": "0",
            "anim_key": 336078,
            "big_jump": "0",
            "anim_points": [
                {
                    "percent": "8",
                    "dir": "232",
                    "lat": 82268154.8,
                    "lon": 152852464
                },
                {
                    "percent": "3",
                    "dir": "236",
                    "lat": 82268212.4,
                    "lon": 152852404
                },
                {
                    "percent": "23",
                    "dir": "229",
                    "lat": 82268570.8,
                    "lon": 152851924
                },
                {
                    "percent": "9",
                    "dir": "225",
                    "lat": 82268698.8,
                    "lon": 152851744
                },
                {
                    "percent": "57",
                    "dir": "228",
                    "lat": 82269588.4,
                    "lon": 152850508
                }
            ]
        },
        {
            "id": "863051062954325",
            "lon": 152925623.5,
            "lat": 82207975.6,
            "dir": 337,
            "speed": 42,
            "lasttime": "12.12.2025 03:19:32",
            "gos_num": "",
            "rid": 240,
            "rnum": "37",
            "rtype": "А",
            "low_floor": "1",
            "wifi": "0",
            "anim_key": 336083,
            "big_jump": "0",
            "anim_points": []
        },
        {
            "id": "866854056212585",
            "lon": 152997533.5,
            "lat": 82180417.2,
            "dir": 217,
            "speed": 19,
            "lasttime": "12.12.2025 03:18:55",
            "gos_num": "",
            "rid": 240,
            "rnum": "37",
            "rtype": "А",
            "low_floor": "1",
            "wifi": "0",
            "anim_key": 336129,
            "big_jump": "0",
            "anim_points": []
        },
        {
            "id": "866854050989857",
            "lon": 152831581,
            "lat": 82281303.6,
            "dir": 297,
            "speed": 17,
            "lasttime": "12.12.2025 03:19:49",
            "gos_num": "",
            "rid": 240,
            "rnum": "37",
            "rtype": "А",
            "low_floor": "0",
            "wifi": "0",
            "anim_key": 336163,
            "big_jump": "0",
            "anim_points": [
                {
                    "percent": "12",
                    "dir": "204",
                    "lat": 82281281.2,
                    "lon": 152831536
                },
                {
                    "percent": "21",
                    "dir": "119",
                    "lat": 82280884.4,
                    "lon": 152831200
                },
                {
                    "percent": "67",
                    "dir": "207",
                    "lat": 82281524.4,
                    "lon": 152829232
                }
            ]
        },
        {
            "id": "863051062952956",
            "lon": 152877187,
            "lat": 82249490.8,
            "dir": 291,
            "speed": 26,
            "lasttime": "12.12.2025 03:19:29",
            "gos_num": "",
            "rid": 240,
            "rnum": "37",
            "rtype": "А",
            "low_floor": "1",
            "wifi": "0",
            "anim_key": 336216,
            "big_jump": "0",
            "anim_points": []
        },
        {
            "id": "863051062856355",
            "lon": 152854073.5,
            "lat": 82267066.8,
            "dir": 312,
            "speed": 15,
            "lasttime": "12.12.2025 03:19:50",
            "gos_num": "",
            "rid": 240,
            "rnum": "37",
            "rtype": "А",
            "low_floor": "1",
            "wifi": "0",
            "anim_key": 336226,
            "big_jump": "0",
            "anim_points": []
        },
        {
            "id": "863051062954325",
            "lon": 152925619,
            "lat": 82207974,
            "dir": 337,
            "speed": 42,
            "lasttime": "12.12.2025 03:19:32",
            "gos_num": "",
            "rid": 240,
            "rnum": "37",
            "rtype": "А",
            "low_floor": "1",
            "wifi": "0",
            "anim_key": 336231,
            "big_jump": "0",
            "anim_points": []
        },
        {
            "id": "866854056212585",
            "lon": 152992820.5,
            "lat": 82176126,
            "dir": 219,
            "speed": 6,
            "lasttime": "12.12.2025 03:20:08",
            "gos_num": "",
            "rid": 240,
            "rnum": "37",
            "rtype": "А",
            "low_floor": "1",
            "wifi": "0",
            "anim_key": 336277,
            "big_jump": "0",
            "anim_points": [
                {
                    "percent": "3",
                    "dir": "129",
                    "lat": 82178753.2,
                    "lon": 152995816
                },
                {
                    "percent": "6",
                    "dir": "128",
                    "lat": 82178548.4,
                    "lon": 152995576
                },
                {
                    "percent": "31",
                    "dir": "125",
                    "lat": 82177383.6,
                    "lon": 152994340
                },
                {
                    "percent": "17",
                    "dir": "127",
                    "lat": 82176775.6,
                    "lon": 152993632
                },
                {
                    "percent": "24",
                    "dir": "125",
                    "lat": 82175905.2,
                    "lon": 152992672
                },
                {
                    "percent": "4",
                    "dir": "127",
                    "lat": 82175738.8,
                    "lon": 152992492
                },
                {
                    "percent": "16",
                    "dir": "129",
                    "lat": 82175156.4,
                    "lon": 152991772
                }
            ]
        },
        {
            "id": "866854050989857",
            "lon": 152831582.5,
            "lat": 82281302,
            "dir": 262,
            "speed": 17,
            "lasttime": "12.12.2025 03:19:49",
            "gos_num": "",
            "rid": 240,
            "rnum": "37",
            "rtype": "А",
            "low_floor": "0",
            "wifi": "0",
            "anim_key": 336311,
            "big_jump": "0",
            "anim_points": []
        },
        {
            "id": "863051062952956",
            "lon": 152875837,
            "lat": 82250484.4,
            "dir": 319,
            "speed": 29,
            "lasttime": "12.12.2025 03:19:52",
            "gos_num": "",
            "rid": 240,
            "rnum": "37",
            "rtype": "А",
            "low_floor": "1",
            "wifi": "0",
            "anim_key": 336515,
            "big_jump": "0",
            "anim_points": []
        },
        {
            "id": "863051062856355",
            "lon": 152849660.5,
            "lat": 82270350,
            "dir": 317,
            "speed": 46,
            "lasttime": "12.12.2025 03:20:27",
            "gos_num": "",
            "rid": 240,
            "rnum": "37",
            "rtype": "А",
            "low_floor": "1",
            "wifi": "0",
            "anim_key": 336526,
            "big_jump": "0",
            "anim_points": [
                {
                    "percent": "6",
                    "dir": "227",
                    "lat": 82269722.8,
                    "lon": 152850328
                },
                {
                    "percent": "51",
                    "dir": "226",
                    "lat": 82270759.6,
                    "lon": 152848804
                },
                {
                    "percent": "43",
                    "dir": "227",
                    "lat": 82271630,
                    "lon": 152847544
                }
            ]
        },
        {
            "id": "863051062954325",
            "lon": 152921705.5,
            "lat": 82214734,
            "dir": 339,
            "speed": 35,
            "lasttime": "12.12.2025 03:20:08",
            "gos_num": "",
            "rid": 240,
            "rnum": "37",
            "rtype": "А",
            "low_floor": "1",
            "wifi": "0",
            "anim_key": 336531,
            "big_jump": "0",
            "anim_points": []
        },
        {
            "id": "866854056212585",
            "lon": 152992819,
            "lat": 82176126,
            "dir": 217,
            "speed": 6,
            "lasttime": "12.12.2025 03:20:08",
            "gos_num": "",
            "rid": 240,
            "rnum": "37",
            "rtype": "А",
            "low_floor": "1",
            "wifi": "0",
            "anim_key": 336575,
            "big_jump": "0",
            "anim_points": []
        },
        {
            "id": "866854050989857",
            "lon": 152831255.5,
            "lat": 82281138.8,
            "dir": 220,
            "speed": 14,
            "lasttime": "12.12.2025 03:19:53",
            "gos_num": "",
            "rid": 240,
            "rnum": "37",
            "rtype": "А",
            "low_floor": "0",
            "wifi": "0",
            "anim_key": 336609,
            "big_jump": "0",
            "anim_points": []
        },
        {
            "id": "863051062952956",
            "lon": 152875837,
            "lat": 82250484.4,
            "dir": 319,
            "speed": 29,
            "lasttime": "12.12.2025 03:19:52",
            "gos_num": "",
            "rid": 240,
            "rnum": "37",
            "rtype": "А",
            "low_floor": "1",
            "wifi": "0",
            "anim_key": 336664,
            "big_jump": "0",
            "anim_points": []
        },
        {
            "id": "863051062856355",
            "lon": 152849660.5,
            "lat": 82270350,
            "dir": 319,
            "speed": 46,
            "lasttime": "12.12.2025 03:20:27",
            "gos_num": "",
            "rid": 240,
            "rnum": "37",
            "rtype": "А",
            "low_floor": "1",
            "wifi": "0",
            "anim_key": 336675,
            "big_jump": "0",
            "anim_points": []
        },
        {
            "id": "863051062954325",
            "lon": 152921705.5,
            "lat": 82214730.8,
            "dir": 339,
            "speed": 35,
            "lasttime": "12.12.2025 03:20:08",
            "gos_num": "",
            "rid": 240,
            "rnum": "37",
            "rtype": "А",
            "low_floor": "1",
            "wifi": "0",
            "anim_key": 336680,
            "big_jump": "0",
            "anim_points": []
        },
        {
            "id": "866854056212585",
            "lon": 152992819,
            "lat": 82176126,
            "dir": 217,
            "speed": 6,
            "lasttime": "12.12.2025 03:20:08",
            "gos_num": "",
            "rid": 240,
            "rnum": "37",
            "rtype": "А",
            "low_floor": "1",
            "wifi": "0",
            "anim_key": 336724,
            "big_jump": "0",
            "anim_points": []
        },
        {
            "id": "866854050989857",
            "lon": 152831255.5,
            "lat": 82281138.8,
            "dir": 220,
            "speed": 14,
            "lasttime": "12.12.2025 03:19:53",
            "gos_num": "",
            "rid": 240,
            "rnum": "37",
            "rtype": "А",
            "low_floor": "0",
            "wifi": "0",
            "anim_key": 336758,
            "big_jump": "0",
            "anim_points": []
        },
        {
            "id": "863051062952956",
            "lon": 152871413.5,
            "lat": 82254038,
            "dir": 320,
            "speed": 15,
            "lasttime": "12.12.2025 03:20:31",
            "gos_num": "",
            "rid": 240,
            "rnum": "37",
            "rtype": "А",
            "low_floor": "1",
            "wifi": "0",
            "anim_key": 336812,
            "big_jump": "0",
            "anim_points": [
                {
                    "percent": "14",
                    "dir": "228",
                    "lat": 82254554.8,
                    "lon": 152870464
                },
                {
                    "percent": "5",
                    "dir": "228",
                    "lat": 82254670,
                    "lon": 152870308
                },
                {
                    "percent": "18",
                    "dir": "230",
                    "lat": 82255066.8,
                    "lon": 152869780
                },
                {
                    "percent": "47",
                    "dir": "230",
                    "lat": 82256103.6,
                    "lon": 152868448
                },
                {
                    "percent": "9",
                    "dir": "231",
                    "lat": 82256308.4,
                    "lon": 152868196
                },
                {
                    "percent": "6",
                    "dir": "230",
                    "lat": 82256449.2,
                    "lon": 152868016
                }
            ]
        },
        {
            "id": "863051062856355",
            "lon": 152849665,
            "lat": 82270351.6,
            "dir": 319,
            "speed": 46,
            "lasttime": "12.12.2025 03:20:27",
            "gos_num": "",
            "rid": 240,
            "rnum": "37",
            "rtype": "А",
            "low_floor": "1",
            "wifi": "0",
            "anim_key": 336823,
            "big_jump": "0",
            "anim_points": []
        },
        {
            "id": "863051062954325",
            "lon": 152921705.5,
            "lat": 82214730.8,
            "dir": 339,
            "speed": 35,
            "lasttime": "12.12.2025 03:20:08",
            "gos_num": "",
            "rid": 240,
            "rnum": "37",
            "rtype": "А",
            "low_floor": "1",
            "wifi": "0",
            "anim_key": 336828,
            "big_jump": "0",
            "anim_points": []
        },
        {
            "id": "866854056212585",
            "lon": 152991836.5,
            "lat": 82175314.8,
            "dir": 317,
            "speed": 20,
            "lasttime": "12.12.2025 03:20:27",
            "gos_num": "",
            "rid": 240,
            "rnum": "37",
            "rtype": "А",
            "low_floor": "1",
            "wifi": "0",
            "anim_key": 336870,
            "big_jump": "0",
            "anim_points": [
                {
                    "percent": "6",
                    "dir": "225",
                    "lat": 82175246,
                    "lon": 152991652
                },
                {
                    "percent": "25",
                    "dir": "224",
                    "lat": 82175604.4,
                    "lon": 152991076
                },
                {
                    "percent": "3",
                    "dir": "225",
                    "lat": 82175655.6,
                    "lon": 152991004
                },
                {
                    "percent": "15",
                    "dir": "226",
                    "lat": 82175873.2,
                    "lon": 152990680
                },
                {
                    "percent": "51",
                    "dir": "227",
                    "lat": 82176647.6,
                    "lon": 152989576
                }
            ]
        },
        {
            "id": "866854050989857",
            "lon": 152831255.5,
            "lat": 82281138.8,
            "dir": 220,
            "speed": 14,
            "lasttime": "12.12.2025 03:19:53",
            "gos_num": "",
            "rid": 240,
            "rnum": "37",
            "rtype": "А",
            "low_floor": "0",
            "wifi": "0",
            "anim_key": 336902,
            "big_jump": "0",
            "anim_points": []
        },
        {
            "id": "863051063288715",
            "lon": 152766088,
            "lat": 82292710,
            "dir": 105,
            "speed": 4,
            "lasttime": "12.12.2025 03:20:21",
            "gos_num": "",
            "rid": 240,
            "rnum": "37",
            "rtype": "А",
            "low_floor": "1",
            "wifi": "0",
            "anim_key": 337094,
            "big_jump": "0",
            "anim_points": []
        },
        {
            "id": "863051062952956",
            "lon": 152871407.5,
            "lat": 82254038,
            "dir": 321,
            "speed": 15,
            "lasttime": "12.12.2025 03:20:31",
            "gos_num": "",
            "rid": 240,
            "rnum": "37",
            "rtype": "А",
            "low_floor": "1",
            "wifi": "0",
            "anim_key": 337103,
            "big_jump": "0",
            "anim_points": []
        },
        {
            "id": "863051062856355",
            "lon": 152847688,
            "lat": 82271746.8,
            "dir": 307,
            "speed": 11,
            "lasttime": "12.12.2025 03:20:48",
            "gos_num": "",
            "rid": 240,
            "rnum": "37",
            "rtype": "А",
            "low_floor": "1",
            "wifi": "0",
            "anim_key": 337114,
            "big_jump": "0",
            "anim_points": []
        },
        {
            "id": "863051062954325",
            "lon": 152917909,
            "lat": 82221287.6,
            "dir": 354,
            "speed": 55,
            "lasttime": "12.12.2025 03:21:00",
            "gos_num": "",
            "rid": 240,
            "rnum": "37",
            "rtype": "А",
            "low_floor": "1",
            "wifi": "0",
            "anim_key": 337119,
            "big_jump": "0",
            "anim_points": [
                {
                    "percent": "2",
                    "dir": "248",
                    "lat": 82216308.4,
                    "lon": 152920684
                },
                {
                    "percent": "2",
                    "dir": "247",
                    "lat": 82216455.6,
                    "lon": 152920600
                },
                {
                    "percent": "2",
                    "dir": "249",
                    "lat": 82216628.4,
                    "lon": 152920504
                },
                {
                    "percent": "14",
                    "dir": "249",
                    "lat": 82217959.6,
                    "lon": 152919712
                },
                {
                    "percent": "21",
                    "dir": "249",
                    "lat": 82219918,
                    "lon": 152918536
                },
                {
                    "percent": "12",
                    "dir": "250",
                    "lat": 82221018.8,
                    "lon": 152917936
                },
                {
                    "percent": "6",
                    "dir": "258",
                    "lat": 82221543.6,
                    "lon": 152917768
                },
                {
                    "percent": "7",
                    "dir": "262",
                    "lat": 82222209.2,
                    "lon": 152917624
                },
                {
                    "percent": "16",
                    "dir": "265",
                    "lat": 82223809.2,
                    "lon": 152917396
                },
                {
                    "percent": "2",
                    "dir": "265",
                    "lat": 82224046,
                    "lon": 152917360
                },
                {
                    "percent": "17",
                    "dir": "264",
                    "lat": 82225690.8,
                    "lon": 152917096
                }
            ]
        },
        {
            "id": "866854056212585",
            "lon": 152991835,
            "lat": 82175314.8,
            "dir": 233,
            "speed": 20,
            "lasttime": "12.12.2025 03:20:27",
            "gos_num": "",
            "rid": 240,
            "rnum": "37",
            "rtype": "А",
            "low_floor": "1",
            "wifi": "0",
            "anim_key": 337161,
            "big_jump": "0",
            "anim_points": []
        },
        {
            "id": "866854050989857",
            "lon": 152831255.5,
            "lat": 82281138.8,
            "dir": 220,
            "speed": 14,
            "lasttime": "12.12.2025 03:19:53",
            "gos_num": "",
            "rid": 240,
            "rnum": "37",
            "rtype": "А",
            "low_floor": "0",
            "wifi": "0",
            "anim_key": 337194,
            "big_jump": "0",
            "anim_points": []
        }
    ]
}